auto_video_cut/__init__.py
auto_video_cut/auto_video_cut.py
auto_video_cut_ybalcanci-0.0.1.dist-info/LICENSE
auto_video_cut_ybalcanci-0.0.1.dist-info/METADATA
auto_video_cut_ybalcanci-0.0.1.dist-info/WHEEL
auto_video_cut_ybalcanci-0.0.1.dist-info/top_level.txt
auto_video_cut_ybalcanci-0.0.1.dist-info/RECORD
